nygen_default/__init__.py
nygen_default/template/LICENSE
nygen_default/template/MANIFEST.in
nygen_default/template/README.md
nygen_default/template/__init__.py
nygen_default/template/pyproject.toml
nygen_default/template/setup.cfg
nygen_default/template/setup.py
nygen_default/template/{_}.gitignore{_}
nygen_default/template/{name}.code-workspace{_}
nygen_default/template/.github{_}/actions/append-buildnum/action.yml
nygen_default/template/.github{_}/actions/find-regex/action.yml
nygen_default/template/.github{_}/actions/metadata/action.yml
nygen_default/template/.github{_}/workflows/publish-to-pypi.yml
nygen_default/template/.github{_}/workflows/publish-to-testpypi.yml
nygen_default/template/.vscode{_}/launch.json
nygen_default/template/.vscode{_}/settings.json
nygen_default/template/docs/doc.txt
nygen_default/template/tests/{name}_test.py{_}
nygen_default/template/{name}/main.py
nygen_default/template/{name}/{_}__init__.py
nygen_default/template/{name}/{_}__main__.py
nygen_default/template/{name}/data/{_}__init__.py
nygen_default/template/{name}/lib/{_}__init__.py
nygen_default-0.0.16.dist-info/LICENSE
nygen_default-0.0.16.dist-info/METADATA
nygen_default-0.0.16.dist-info/WHEEL
nygen_default-0.0.16.dist-info/entry_points.txt
nygen_default-0.0.16.dist-info/top_level.txt
nygen_default-0.0.16.dist-info/zip-safe
nygen_default-0.0.16.dist-info/RECORD
