Metadata-Version: 2.1
Name: nygen-default
Version: 0.0.16
Summary: nygen-default
Home-page: UNKNOWN
Author: Natalie Fearnley
Author-email: nfearnley@gmail.com
License: MIT
Project-URL: Source, https://github.com/nfearnley/nygen-default
Project-URL: Tracker, https://github.com/nfearnley/nygen-default/issues
Platform: any
Classifier: Programming Language :: Python
Classifier: Operating System :: OS Independent
Classifier: License :: OSI Approved :: MIT License
